allie/__init__.py
allie/allie.py
allie-1.1.3.data/data/Lib/site-packages/allie/ALLIEToken/ArduinoToken.txt
allie-1.1.3.data/data/Lib/site-packages/allie/ALLIE_Falas_Offline/ALLIE sond.mp3
allie-1.1.3.data/data/Lib/site-packages/allie/ALLIE_Falas_Offline/ALLIEConexaoOk.mp3
allie-1.1.3.data/data/Lib/site-packages/allie/ALLIE_Falas_Offline/ALLIEConfigNot.mp3
allie-1.1.3.data/data/Lib/site-packages/allie/ALLIE_Falas_Offline/ALLIERead.mp3
allie-1.1.3.data/data/Lib/site-packages/allie/ALLIE_Falas_Offline/ALLIErrorConect.mp3
allie-1.1.3.data/data/Lib/site-packages/allie/ALLIE_Falas_Offline/Problema de rede.mp3
allie-1.1.3.data/data/Lib/site-packages/allie/confg/config.json
allie-1.1.3.data/data/Lib/site-packages/allie/conversas/I.A dialog.txt
allie-1.1.3.data/data/Lib/site-packages/allie/conversas/origens.txt
allie-1.1.3.data/scripts/createFolder.py
allie-1.1.3.dist-info/METADATA
allie-1.1.3.dist-info/RECORD
allie-1.1.3.dist-info/WHEEL
allie-1.1.3.dist-info/top_level.txt
