Metadata-Version: 2.1
Name: allie
Version: 1.1.3
Summary: Biblioteca de inteligência artificial
Home-page: https://youtube.com/tdcprojetos
Author: Klinsman Jorge
Author-email: tdcprojetos@hotmail.com
License: MIT
Platform: UNKNOWN
Classifier: License :: OSI Approved :: MIT License
Classifier: Programming Language :: Python :: 3.4
Classifier: Programming Language :: Python :: 3.5
Classifier: Programming Language :: Python :: 3.6
Requires-Dist: wikipedia
Requires-Dist: requests
Requires-Dist: boto3
Requires-Dist: python-vlc
Requires-Dist: chatterbot
Requires-Dist: pyserial
Requires-Dist: speechrecognition
Requires-Dist: google-speech
Requires-Dist: pypiwin32
Requires-Dist: pyttsx3
